setup.py
email/header.py
micropython_email.header.egg-info/PKG-INFO
micropython_email.header.egg-info/SOURCES.txt
micropython_email.header.egg-info/dependency_links.txt
micropython_email.header.egg-info/requires.txt
micropython_email.header.egg-info/top_level.txt