Metadata-Version: 1.0
Name: micropython-email.header
Version: 0.5.1
Summary: CPython email.header module ported to MicroPython
Home-page: https://github.com/micropython/micropython/issues/405
Author: MicroPython Developers
Author-email: micro-python@googlegroups.com
License: Python
Platform: UNKNOWN
